mycalc/calculator.py
pnzxefene-0.0.2.dist-info/METADATA
pnzxefene-0.0.2.dist-info/WHEEL
pnzxefene-0.0.2.dist-info/top_level.txt
pnzxefene-0.0.2.dist-info/RECORD
