Metadata-Version: 2.1
Name: pnzxefene
Version: 0.0.2
Summary: nice calculator
Home-page: https://github.com/pnzx/calc0001
Download-URL: https://github.com/pnzx/calc0001/
Author: pnzx
Classifier: Programming Language :: Python :: 3
